toppy/__init__.py
toppy/toppy.py
toppy/plot/__init__.py
toppy/plot/animated.py
toppy/plot/common.py
toppy/plot/cpu_plotter.py
toppy/plot/gpu_plotter.py
toppy/plot/io_plotter.py
toppy/plot/memory_plotter.py
toppy/plot/network_plotter.py
toppy/system_stat/__init__.py
toppy/system_stat/cpu_stat.py
toppy/system_stat/gpu_stat.py
toppy/system_stat/io_stat.py
toppy/system_stat/mem_stat.py
toppy/system_stat/network_stat.py
toppy-0.1.4.data/scripts/toppy
toppy-0.1.4.dist-info/LICENSE
toppy-0.1.4.dist-info/METADATA
toppy-0.1.4.dist-info/WHEEL
toppy-0.1.4.dist-info/top_level.txt
toppy-0.1.4.dist-info/RECORD
