Metadata-Version: 2.1
Name: toppy
Version: 0.1.4
Summary: Graphical system resources monitor in python
Home-page: https://github.com/gabay/toppy
Author: Roi Gabay
Author-email: roigby@gmail.com
License: MIT
Platform: UNKNOWN
Classifier: Programming Language :: Python :: 3
Classifier: License :: OSI Approved :: MIT License
Classifier: Operating System :: OS Independent
Requires-Python: >=3.6
Requires-Dist: matplotlib (<4,>=3.3.4)
Requires-Dist: psutil (<6,>=5.8.0)
Requires-Dist: gpustat (<1,>=0.6.0)
